[{
  "_id": {
    "$oid": "636f47753b55cba4e941d985"
  },
  "shippingInfo": {
    "address": "Ernakulam\nKerala\n682001",
    "city": "Ernakulam",
    "phone": {
      "$numberLong": "9562935099"
    },
    "postalCode": "682006",
    "state": "Kerala",
    "district": "Ernakulam",
    "country": "India"
  },
  "user": {
    "$oid": "634812989d09660f253cff48"
  },
  "orderItems": [
    {
      "name": "Potato",
      "quantity": 2,
      "image": "https://res.cloudinary.com/farmershub/image/upload/v1666186947/products/jcbyb1lag6dzdb94gnb9.webp",
      "price": 4500,
      "product": {
        "$oid": "634ffecde8c67c8df7cfb9eb"
      },
      "_id": {
        "$oid": "636f47753b55cba4e941d986"
      }
    },
    {
      "name": "Lettuce",
      "quantity": 3,
      "image": "https://res.cloudinary.com/farmershub/image/upload/v1667811809/products/39186425c56cc5ace27d8517298323d8.jpg",
      "price": 2500,
      "product": {
        "$oid": "6368c9e46cf4706a25553f02"
      },
      "_id": {
        "$oid": "636f47753b55cba4e941d987"
      }
    },
    {
      "name": "Pumpkin",
      "quantity": 1,
      "image": "https://res.cloudinary.com/farmershub/image/upload/v1666187072/products/xw4xxdl6ugbf8c4zohkv.webp",
      "price": 2500,
      "product": {
        "$oid": "634fff43e8c67c8df7cfb9fd"
      },
      "_id": {
        "$oid": "636f47753b55cba4e941d988"
      }
    }
  ],
  "paymentInfo": {
    "id": "pay_Kf2a56BDQv0L3F",
    "status": "success",
    "refund_id": ""
  },
  "paidAt": {
    "$date": {
      "$numberLong": "1662966773010"
    }
  },
  "itemsPrice": 19000,
  "taxPrice": 570,
  "shippingPrice": 1167,
  "totalPrice": 20737,
  "orderStatus": "Delivered",
  "createdAt": {
    "$date": {
      "$numberLong": "1664521973036"
    }
  },
  "__v": 0,
  "deliveredAt": {
    "$date": {
      "$numberLong": "1665893939807"
    }
  }
},{
  "_id": {
    "$oid": "636f49003b55cba4e941deba"
  },
  "shippingInfo": {
    "address": "Ernakulam\nKerala\n682001",
    "city": "Ernakulam",
    "phone": {
      "$numberLong": "9562935099"
    },
    "postalCode": "682006",
    "state": "Kerala",
    "district": "Ernakulam",
    "country": "India"
  },
  "user": {
    "$oid": "634812989d09660f253cff48"
  },
  "orderItems": [
    {
      "name": "Tapioca",
      "quantity": 1,
      "image": "https://res.cloudinary.com/farmershub/image/upload/v1667818757/products/7f2c144c68f6bbe5644cf2c0ade8765d.jpg",
      "price": 3500,
      "product": {
        "$oid": "6368e509f15d8a192a8f1025"
      },
      "_id": {
        "$oid": "636f49003b55cba4e941debb"
      }
    },
    {
      "name": "Grapes Black",
      "quantity": 1,
      "image": "https://res.cloudinary.com/farmershub/image/upload/v1667818583/products/4a7cf7617f70ce9770e4ca641e9ad939.jpg",
      "price": 10000,
      "product": {
        "$oid": "6368e459f15d8a192a8f0e98"
      },
      "_id": {
        "$oid": "636f49003b55cba4e941debc"
      }
    },
    {
      "name": "Garlic",
      "quantity": 2,
      "image": "https://res.cloudinary.com/farmershub/image/upload/v1667818384/products/1c8d2b5b51418587775baed63285d64d.jpg",
      "price": 1500,
      "product": {
        "$oid": "6368e393f15d8a192a8f0c39"
      },
      "_id": {
        "$oid": "636f49003b55cba4e941debd"
      }
    },
    {
      "name": "Pomogranite",
      "quantity": 1,
      "image": "https://res.cloudinary.com/farmershub/image/upload/v1667809643/products/aafeae3773dc6e0feb27ce9fdcd3e12c.jpg",
      "price": 15000,
      "product": {
        "$oid": "6368c16e6cf4706a25553955"
      },
      "_id": {
        "$oid": "636f49003b55cba4e941debe"
      }
    }
  ],
  "paymentInfo": {
    "id": "pay_Kf2h2d6WieiXxB",
    "status": "success",
    "refund_id": "rfnd_Kf2hnDxhQZ59Cd"
  },
  "paidAt": {
    "$date": {
      "$numberLong": "1663139968687"
    }
  },
  "itemsPrice": 31500,
  "taxPrice": 945,
  "shippingPrice": 2000,
  "totalPrice": 1033,
  "orderStatus": "Refunded",
  "createdAt": {
    "$date": {
      "$numberLong": "1663139968696"
    }
  },
  "__v": 0
},{
  "_id": {
    "$oid": "636f4a9d44d4d4717e604669"
  },
  "shippingInfo": {
    "address": "Ernakulam\nKerala\n682001",
    "city": "Ernakulam",
    "phone": {
      "$numberLong": "9562935099"
    },
    "postalCode": "682006",
    "state": "Kerala",
    "district": "Ernakulam",
    "country": "India"
  },
  "user": {
    "$oid": "634812989d09660f253cff48"
  },
  "orderItems": [
    {
      "name": "Tapioca",
      "quantity": 2,
      "image": "https://res.cloudinary.com/farmershub/image/upload/v1667818757/products/7f2c144c68f6bbe5644cf2c0ade8765d.jpg",
      "price": 3500,
      "product": {
        "$oid": "6368e509f15d8a192a8f1025"
      },
      "_id": {
        "$oid": "636f4a9d44d4d4717e60466a"
      }
    },
    {
      "name": "Cucumber",
      "quantity": 1,
      "image": "https://res.cloudinary.com/farmershub/image/upload/v1666529883/products/28cac140df83a2e0b59d995d5ea44b07.jpg",
      "price": 4000,
      "product": {
        "$oid": "63553a5e6567a52dfa7b9391"
      },
      "_id": {
        "$oid": "636f4a9d44d4d4717e60466b"
      }
    },
    {
      "name": "Rambuttan",
      "quantity": 2,
      "image": "https://res.cloudinary.com/farmershub/image/upload/v1667815223/products/15b4dced660f6b8390e22e71a10ff10f.jpg",
      "price": 10000,
      "product": {
        "$oid": "6368d73bf15d8a192a8f0469"
      },
      "_id": {
        "$oid": "636f4a9d44d4d4717e60466c"
      }
    },
    {
      "name": "Spring Onion",
      "quantity": 2,
      "image": "https://res.cloudinary.com/farmershub/image/upload/v1667811390/products/d217221aeec1eea3264e25125d47bba9.jpg",
      "price": 1000,
      "product": {
        "$oid": "6368c8416cf4706a25553bae"
      },
      "_id": {
        "$oid": "636f4a9d44d4d4717e60466d"
      }
    },
    {
      "name": "Papaya",
      "quantity": 2,
      "image": "https://res.cloudinary.com/farmershub/image/upload/v1667812182/products/12a40a50e08daee85a33226089d50859.jpg",
      "price": 4000,
      "product": {
        "$oid": "6368cb5c68b55609dcd438e2"
      },
      "_id": {
        "$oid": "636f4a9d44d4d4717e60466e"
      }
    },
    {
      "name": "Alphonsa Mango",
      "quantity": 1,
      "image": "https://res.cloudinary.com/farmershub/image/upload/v1667811204/products/f6cc1bb4b44f51826876f89600f94ac3.webp",
      "price": 7500,
      "product": {
        "$oid": "6368c7896cf4706a25553b83"
      },
      "_id": {
        "$oid": "636f4a9d44d4d4717e60466f"
      }
    }
  ],
  "paymentInfo": {
    "id": "pay_Kf2oIcUQAHZ9L5",
    "status": "success",
    "refund_id": ""
  },
  "paidAt": {
    "$date": {
      "$numberLong": "1665559581066"
    }
  },
  "itemsPrice": 48500,
  "taxPrice": 1455,
  "shippingPrice": 3333,
  "totalPrice": 53288,
  "orderStatus": "Delivered",
  "createdAt": {
    "$date": {
      "$numberLong": "1665818781091"
    }
  },
  "__v": 0,
  "deliveredAt": {
    "$date": {
      "$numberLong": "1665980171882"
    }
  }
},{
  "_id": {
    "$oid": "6374607ee206fbe74d48e4b8"
  },
  "shippingInfo": {
    "address": "Ernakulam\nKerala\n682001",
    "city": "Ernakulam",
    "phone": {
      "$numberLong": "9562935099"
    },
    "postalCode": "682006",
    "state": "Kerala",
    "district": "Ernakulam",
    "country": "India"
  },
  "user": {
    "$oid": "635cf16574e265607466c765"
  },
  "orderItems": [
    {
      "name": "Dragon Fruit",
      "quantity": 3,
      "image": "https://res.cloudinary.com/farmershub/image/upload/v1667817082/products/e9eac395f3984b44cc799d1191e5f7cd.jpg",
      "price": 5000,
      "product": {
        "$oid": "6368de86f15d8a192a8f094a"
      },
      "_id": {
        "$oid": "6374607ee206fbe74d48e4b9"
      }
    },
    {
      "name": "Alphonsa Mango",
      "quantity": 2,
      "image": "https://res.cloudinary.com/farmershub/image/upload/v1667811204/products/f6cc1bb4b44f51826876f89600f94ac3.webp",
      "price": 7500,
      "product": {
        "$oid": "6368c7896cf4706a25553b83"
      },
      "_id": {
        "$oid": "6374607ee206fbe74d48e4ba"
      }
    },
    {
      "name": "Orange",
      "quantity": 1,
      "image": "https://res.cloudinary.com/farmershub/image/upload/v1667819176/products/c30ee1a63aa3d18bda960daaf269b125.webp",
      "price": 7000,
      "product": {
        "$oid": "6368e661f15d8a192a8f12ce"
      },
      "_id": {
        "$oid": "6374607ee206fbe74d48e4bb"
      }
    }
  ],
  "paymentInfo": {
    "id": "pay_KgZRsnSWfnbCKb",
    "status": "success",
    "refund_id": ""
  },
  "paidAt": {
    "$date": {
      "$numberLong": "1666238462777"
    }
  },
  "itemsPrice": 37000,
  "taxPrice": 1110,
  "shippingPrice": 2333,
  "totalPrice": 40443,
  "orderStatus": "Delivered",
  "createdAt": {
    "$date": {
      "$numberLong": "1666238462795"
    }
  },
  "__v": 0,
  "deliveredAt": {
    "$date": {
      "$numberLong": "1666325764088"
    }
  }
},{
  "_id": {
    "$oid": "6374638b6f0dc5aca4c16be9"
  },
  "shippingInfo": {
    "address": "Ernakulam\nKerala\n682001",
    "city": "Vypin",
    "phone": {
      "$numberLong": "9875687950"
    },
    "postalCode": "682343",
    "state": "Kerala",
    "district": "Ernakulam",
    "country": "India"
  },
  "user": {
    "$oid": "637460fbe206fbe74d48e625"
  },
  "orderItems": [
    {
      "name": "Mango",
      "quantity": 2,
      "image": "https://res.cloudinary.com/farmershub/image/upload/v1666187387/products/jc7rwzrquemizksphu7o.jpg",
      "price": 6000,
      "product": {
        "$oid": "63500081955b781df9b26cf4"
      },
      "_id": {
        "$oid": "6374638b6f0dc5aca4c16bea"
      }
    },
    {
      "name": "Grapes Black",
      "quantity": 1,
      "image": "https://res.cloudinary.com/farmershub/image/upload/v1667818583/products/4a7cf7617f70ce9770e4ca641e9ad939.jpg",
      "price": 10000,
      "product": {
        "$oid": "6368e459f15d8a192a8f0e98"
      },
      "_id": {
        "$oid": "6374638b6f0dc5aca4c16beb"
      }
    },
    {
      "name": "Green Grapes",
      "quantity": 2,
      "image": "https://res.cloudinary.com/farmershub/image/upload/v1667818491/products/716366991cb6b853a4509cbd66e94a44.jpg",
      "price": 13000,
      "product": {
        "$oid": "6368e40ff15d8a192a8f0d94"
      },
      "_id": {
        "$oid": "6374638b6f0dc5aca4c16bec"
      }
    }
  ],
  "paymentInfo": {
    "id": "pay_KgZfTdclLI1dvf",
    "status": "success",
    "refund_id": ""
  },
  "paidAt": {
    "$date": {
      "$numberLong": "1666325643771"
    }
  },
  "itemsPrice": 48000,
  "taxPrice": 1440,
  "shippingPrice": 1500,
  "totalPrice": 50940,
  "orderStatus": "Delivered",
  "createdAt": {
    "$date": {
      "$numberLong": "1666325643788"
    }
  },
  "__v": 0,
  "deliveredAt": {
    "$date": {
      "$numberLong": "1666498556397"
    }
  }
},{
  "_id": {
    "$oid": "637467cb74a9341641ba4754"
  },
  "shippingInfo": {
    "address": "Ernakulam\nKerala\n682343",
    "city": "Aluva",
    "phone": {
      "$numberLong": "7988967899"
    },
    "postalCode": "682343",
    "state": "Kerala",
    "district": "Ernakulam",
    "country": "India"
  },
  "user": {
    "$oid": "63746709021173f53c43860a"
  },
  "orderItems": [
    {
      "name": "Sweet Potato",
      "quantity": 4,
      "image": "https://res.cloudinary.com/farmershub/image/upload/v1667818858/products/aeea8a89e149da99da6653aac8c2ad08.webp",
      "price": 1800,
      "product": {
        "$oid": "6368e5a9f15d8a192a8f1070"
      },
      "_id": {
        "$oid": "637467cb74a9341641ba4755"
      }
    },
    {
      "name": "Tapioca",
      "quantity": 2,
      "image": "https://res.cloudinary.com/farmershub/image/upload/v1667818757/products/7f2c144c68f6bbe5644cf2c0ade8765d.jpg",
      "price": 3500,
      "product": {
        "$oid": "6368e509f15d8a192a8f1025"
      },
      "_id": {
        "$oid": "637467cb74a9341641ba4756"
      }
    }
  ],
  "paymentInfo": {
    "id": "pay_KgZyq9nJkEM5PJ",
    "status": "success",
    "refund_id": ""
  },
  "paidAt": {
    "$date": {
      "$numberLong": "1668573131026"
    }
  },
  "itemsPrice": 14200,
  "taxPrice": 426,
  "shippingPrice": 1500,
  "totalPrice": 16126,
  "orderStatus": "Shipped",
  "createdAt": {
    "$date": {
      "$numberLong": "1668573131041"
    }
  },
  "__v": 0
},{
  "_id": {
    "$oid": "63746b1814440167f9d92416"
  },
  "shippingInfo": {
    "address": "Ernakulam\nKerala\n682343",
    "city": "Aluva",
    "phone": {
      "$numberLong": "7988967899"
    },
    "postalCode": "682343",
    "state": "Kerala",
    "district": "Ernakulam",
    "country": "India"
  },
  "user": {
    "$oid": "63746af414440167f9d923cb"
  },
  "orderItems": [
    {
      "name": "Coconut",
      "quantity": 4,
      "image": "https://res.cloudinary.com/farmershub/image/upload/v1667809893/products/dbb3c3bc1cf06dadb5b8185419310a45.jpg",
      "price": 10000,
      "product": {
        "$oid": "6368c26a6cf4706a255539de"
      },
      "_id": {
        "$oid": "63746b1814440167f9d92417"
      }
    }
  ],
  "paymentInfo": {
    "id": "pay_KgaDj90YowXfRY",
    "status": "success",
    "refund_id": ""
  },
  "paidAt": {
    "$date": {
      "$numberLong": "1668573976866"
    }
  },
  "itemsPrice": 40000,
  "taxPrice": 1200,
  "shippingPrice": 2500,
  "totalPrice": 43700,
  "orderStatus": "Shipped",
  "createdAt": {
    "$date": {
      "$numberLong": "1668573976874"
    }
  },
  "__v": 0
}]